setup.py
cms/__init__.py
cms/admin.py
cms/models.py
cms/settings.py
cms/tests.py
cms/urls.py
cms/views.py
cms/migrations/0001_initial.py
cms/migrations/0002_auto__add_field_page_parent.py
cms/migrations/0003_auto__add_field_page_is_template.py
cms/migrations/0004_auto__add_field_page_description.py
cms/migrations/__init__.py
cms/templatetags/__init__.py
cms/templatetags/cms_tags.py
django_mini_cms.egg-info/PKG-INFO
django_mini_cms.egg-info/SOURCES.txt
django_mini_cms.egg-info/dependency_links.txt
django_mini_cms.egg-info/requires.txt
django_mini_cms.egg-info/top_level.txt