Metadata-Version: 1.0
Name: django-mini-cms
Version: 0.0.3
Summary: Minimalistic django cms
Home-page: https://github.com/noxan/django-mini-cms
Author: noxan
Author-email: noxan@redmoonstudios.de
License: BSD License
Platform: OS Independent
